captura/__init__.py
captura/__main__.py
captura/auth.py
captura/config.py
captura/controllers/__init__.py
captura/controllers/access.py
captura/controllers/base.py
captura/controllers/create.py
captura/controllers/delete.py
captura/controllers/read.py
captura/depends.py
captura/err.py
captura/fields.py
captura/hooks.py
captura/logger.py
captura/logging.yaml
captura/models.py
captura/schemas.py
captura/static/404.html
captura/static/assets/style.css
captura/static/docker-mark-blue.svg
captura/static/err.css
captura/static/nord.css
captura/static/wavey/wavey-nord0-nord1-nord10.svg
captura/static/wavey/wavey-nord0-nord1-nord7.svg
captura/static/wavey/wavey-nord0-nord1.svg
captura/static/wavey/wavey-nord0.svg
captura/static/wavey/wavey-nord1-nord0.svg
captura/static/wavey/wavey-nord1-nord7-nord10.svg
captura/util.py
captura/views/__init__.py
captura/views/args.py
captura/views/assignments.py
captura/views/auth.py
captura/views/base.py
captura/views/collections.py
captura/views/documents.py
captura/views/events.py
captura/views/grants.py
captura/views/templates/base.j2
captura/views/templates/demo.j2
captura/views/templates/index.j2
captura/views/templates/profile.j2
captura/views/templates/register.j2
captura/views/users.py
legere/__init__.py
legere/__main__.py
legere/apply.py
legere/config.py
legere/flags.py
legere/handlers.py
legere/hooks.py
legere/requests/__init__.py
legere/requests/assignments.py
legere/requests/base.py
legere/requests/collections.py
legere/requests/documents.py
legere/requests/events.py
legere/requests/grants.py
legere/requests/tokens.py
legere/requests/users.py
legere/requests/util.py
simulatus/__init__.py
simulatus/__main__.py
simulatus/assets/assignment.yaml
simulatus/assets/collection.yaml
simulatus/assets/document.yaml
simulatus/assets/event.yaml
simulatus/assets/grant.yaml
simulatus/assets/user.yaml
simulatus/config.py
simulatus/mk.py
simulatus/reports.py
captura-0.1.10.dist-info/METADATA
captura-0.1.10.dist-info/WHEEL
captura-0.1.10.dist-info/entry_points.txt
captura-0.1.10.dist-info/RECORD
