Metadata-Version: 2.1
Name: captura
Version: 0.1.10
Summary: A framework for adding sharing and collections to existing API projects.
License: MIT
Author: Adrian Cederberg
Author-email: adrn.cederberg123@gmail.com
Requires-Python: >=3.11,<4.0
Classifier: License :: OSI Approved :: MIT License
Classifier: Programming Language :: Python :: 3
Classifier: Programming Language :: Python :: 3.11
Classifier: Programming Language :: Python :: 3.12
Classifier: Programming Language :: Python :: 3.13
Requires-Dist: PyMySQL[rsa] (>=1.1.1,<2.0.0)
Requires-Dist: SQLAlchemy (>=2.0.32,<3.0.0)
Requires-Dist: fastapi (>=0.112.0,<0.113.0)
Requires-Dist: httpx (>=0.27.0,<0.28.0)
Requires-Dist: itsdangerous (>=2.2.0,<3.0.0)
Requires-Dist: jinja2 (>=3.1.4,<4.0.0)
Requires-Dist: pydantic (>=2.8.2,<3.0.0)
Requires-Dist: pydantic-settings (>=2.4.0,<3.0.0)
Requires-Dist: pyjwt (>=2.9.0,<3.0.0)
Requires-Dist: python-multipart (>=0.0.9,<0.0.10)
Requires-Dist: rich (>=13.7.1,<14.0.0)
Requires-Dist: typer (>=0.12.3,<0.13.0)
Requires-Dist: types-pyyaml (>=6.0.12.20240808,<7.0.0.0)
Requires-Dist: uvicorn (>=0.30.5,<0.31.0)
Requires-Dist: yaml-settings-pydantic (>=2.3.2,<3.0.0)
